{
  "ticker": "MOLI",
  "sector": "Consumer Defensive",
  "industry": "Packaged Foods",
  "market_cap": "474.33B",
  "pe_ratio": "308.65",
  "dividend_yield": "20.82%",
  "eps": "7.63",
  "beta": "-0.11",
  "price_to_book": "1.89",
  "profit_margin": "-4.28%",
  "description": "Molinos Rio de la Plata S.A. engages in the industrialization and commercialization of food and alcoholic beverages in Argentina and internationally. It operates through Foods and Wineries segments. The company offers edible oils, pasta, dried, frozen, fractionated flour, grass, rice, wines, and sparkling wines. Molinos Rio de la Plata S.A. was incorporated in 1931 and is based in Buenos Aires, Argentina."
}