[
  {
    "date": "2026-04-17",
    "open": 5635.0,
    "high": 5765.0,
    "low": 5635.0,
    "close": 5725.0,
    "volume": 0.0,
    "sma20": null,
    "sma50": null,
    "rsi": null,
    "bb_upper": null,
    "bb_lower": null,
    "bb_middle": null,
    "macd": null,
    "macd_signal": null,
    "macd_hist": null
  },
  {
    "date": "2026-04-21",
    "open": 5880.0,
    "high": 5930.0,
    "low": 5735.0,
    "close": 5755.0,
    "volume": 19964.0,
    "sma20": null,
    "sma50": null,
    "rsi": null,
    "bb_upper": null,
    "bb_lower": null,
    "bb_middle": null,
    "macd": null,
    "macd_signal": null,
    "macd_hist": null
  },
  {
    "date": "2026-04-22",
    "open": 5860.0,
    "high": 5995.0,
    "low": 5825.0,
    "close": 5990.0,
    "volume": 20038.0,
    "sma20": null,
    "sma50": null,
    "rsi": null,
    "bb_upper": null,
    "bb_lower": null,
    "bb_middle": null,
    "macd": null,
    "macd_signal": null,
    "macd_hist": null
  },
  {
    "date": "2026-04-23",
    "open": 5990.0,
    "high": 5995.0,
    "low": 5705.0,
    "close": 5785.0,
    "volume": 7705.0,
    "sma20": null,
    "sma50": null,
    "rsi": null,
    "bb_upper": null,
    "bb_lower": null,
    "bb_middle": null,
    "macd": null,
    "macd_signal": null,
    "macd_hist": null
  },
  {
    "date": "2026-04-24",
    "open": 5805.0,
    "high": 5905.0,
    "low": 5800.0,
    "close": 5890.0,
    "volume": 6361.0,
    "sma20": null,
    "sma50": null,
    "rsi": null,
    "bb_upper": null,
    "bb_lower": null,
    "bb_middle": null,
    "macd": null,
    "macd_signal": null,
    "macd_hist": null
  },
  {
    "date": "2026-04-27",
    "open": 5915.0,
    "high": 6105.0,
    "low": 5910.0,
    "close": 6100.0,
    "volume": 6628.0,
    "sma20": null,
    "sma50": null,
    "rsi": null,
    "bb_upper": null,
    "bb_lower": null,
    "bb_middle": null,
    "macd": null,
    "macd_signal": null,
    "macd_hist": null
  },
  {
    "date": "2026-04-28",
    "open": 5995.0,
    "high": 6050.0,
    "low": 5855.0,
    "close": 5870.0,
    "volume": 2744.0,
    "sma20": null,
    "sma50": null,
    "rsi": null,
    "bb_upper": null,
    "bb_lower": null,
    "bb_middle": null,
    "macd": null,
    "macd_signal": null,
    "macd_hist": null
  },
  {
    "date": "2026-04-29",
    "open": 5850.0,
    "high": 5850.0,
    "low": 5700.0,
    "close": 5720.0,
    "volume": 4976.0,
    "sma20": null,
    "sma50": null,
    "rsi": null,
    "bb_upper": null,
    "bb_lower": null,
    "bb_middle": null,
    "macd": null,
    "macd_signal": null,
    "macd_hist": null
  },
  {
    "date": "2026-04-30",
    "open": 5800.0,
    "high": 5960.0,
    "low": 5725.0,
    "close": 5935.0,
    "volume": 20300.0,
    "sma20": null,
    "sma50": null,
    "rsi": null,
    "bb_upper": null,
    "bb_lower": null,
    "bb_middle": null,
    "macd": null,
    "macd_signal": null,
    "macd_hist": null
  },
  {
    "date": "2026-05-04",
    "open": 5955.0,
    "high": 5955.0,
    "low": 5825.0,
    "close": 5850.0,
    "volume": 9462.0,
    "sma20": null,
    "sma50": null,
    "rsi": null,
    "bb_upper": null,
    "bb_lower": null,
    "bb_middle": null,
    "macd": null,
    "macd_signal": null,
    "macd_hist": null
  },
  {
    "date": "2026-05-05",
    "open": 5905.0,
    "high": 5960.0,
    "low": 5855.0,
    "close": 5900.0,
    "volume": 6677.0,
    "sma20": null,
    "sma50": null,
    "rsi": null,
    "bb_upper": null,
    "bb_lower": null,
    "bb_middle": null,
    "macd": null,
    "macd_signal": null,
    "macd_hist": null
  },
  {
    "date": "2026-05-06",
    "open": 6010.0,
    "high": 6140.0,
    "low": 5965.0,
    "close": 6140.0,
    "volume": 14494.0,
    "sma20": null,
    "sma50": null,
    "rsi": null,
    "bb_upper": null,
    "bb_lower": null,
    "bb_middle": null,
    "macd": null,
    "macd_signal": null,
    "macd_hist": null
  },
  {
    "date": "2026-05-07",
    "open": 6200.0,
    "high": 6200.0,
    "low": 5975.0,
    "close": 5980.0,
    "volume": 13702.0,
    "sma20": null,
    "sma50": null,
    "rsi": null,
    "bb_upper": null,
    "bb_lower": null,
    "bb_middle": null,
    "macd": null,
    "macd_signal": null,
    "macd_hist": null
  },
  {
    "date": "2026-05-08",
    "open": 6045.0,
    "high": 6105.0,
    "low": 5970.0,
    "close": 5985.0,
    "volume": 4255.0,
    "sma20": null,
    "sma50": null,
    "rsi": null,
    "bb_upper": null,
    "bb_lower": null,
    "bb_middle": null,
    "macd": null,
    "macd_signal": null,
    "macd_hist": null
  },
  {
    "date": "2026-05-11",
    "open": 6010.0,
    "high": 6225.0,
    "low": 6010.0,
    "close": 6165.0,
    "volume": 8321.0,
    "sma20": null,
    "sma50": null,
    "rsi": 60.48,
    "bb_upper": null,
    "bb_lower": null,
    "bb_middle": null,
    "macd": null,
    "macd_signal": null,
    "macd_hist": null
  },
  {
    "date": "2026-05-12",
    "open": 6070.0,
    "high": 6125.0,
    "low": 5895.0,
    "close": 6085.0,
    "volume": 5235.0,
    "sma20": null,
    "sma50": null,
    "rsi": 58.09,
    "bb_upper": null,
    "bb_lower": null,
    "bb_middle": null,
    "macd": null,
    "macd_signal": null,
    "macd_hist": null
  },
  {
    "date": "2026-05-13",
    "open": 6110.0,
    "high": 6185.0,
    "low": 6025.0,
    "close": 6125.0,
    "volume": 29383.0,
    "sma20": null,
    "sma50": null,
    "rsi": 58.96,
    "bb_upper": null,
    "bb_lower": null,
    "bb_middle": null,
    "macd": null,
    "macd_signal": null,
    "macd_hist": null
  },
  {
    "date": "2026-05-14",
    "open": 6065.0,
    "high": 6065.0,
    "low": 5955.0,
    "close": 5975.0,
    "volume": 17179.0,
    "sma20": null,
    "sma50": null,
    "rsi": 54.4,
    "bb_upper": null,
    "bb_lower": null,
    "bb_middle": null,
    "macd": null,
    "macd_signal": null,
    "macd_hist": null
  },
  {
    "date": "2026-05-15",
    "open": 5815.0,
    "high": 5815.0,
    "low": 5690.0,
    "close": 5735.0,
    "volume": 13457.0,
    "sma20": null,
    "sma50": null,
    "rsi": 48.0,
    "bb_upper": null,
    "bb_lower": null,
    "bb_middle": null,
    "macd": null,
    "macd_signal": null,
    "macd_hist": null
  },
  {
    "date": "2026-05-18",
    "open": 5760.0,
    "high": 5760.0,
    "low": 5535.0,
    "close": 5600.0,
    "volume": 35559.0,
    "sma20": 5915.5,
    "sma50": null,
    "rsi": 44.8,
    "bb_upper": 6229.97,
    "bb_lower": 5601.03,
    "bb_middle": 5915.5,
    "macd": null,
    "macd_signal": null,
    "macd_hist": null
  },
  {
    "date": "2026-05-19",
    "open": 5505.0,
    "high": 5530.0,
    "low": 5395.0,
    "close": 5465.0,
    "volume": 10652.0,
    "sma20": 5902.5,
    "sma50": null,
    "rsi": 41.81,
    "bb_upper": 6265.19,
    "bb_lower": 5539.81,
    "bb_middle": 5902.5,
    "macd": null,
    "macd_signal": null,
    "macd_hist": null
  },
  {
    "date": "2026-05-20",
    "open": 5480.0,
    "high": 5625.0,
    "low": 5475.0,
    "close": 5600.0,
    "volume": 9603.0,
    "sma20": 5894.75,
    "sma50": null,
    "rsi": 45.72,
    "bb_upper": 6275.87,
    "bb_lower": 5513.63,
    "bb_middle": 5894.75,
    "macd": null,
    "macd_signal": null,
    "macd_hist": null
  },
  {
    "date": "2026-05-21",
    "open": 5630.0,
    "high": 5760.0,
    "low": 5575.0,
    "close": 5695.0,
    "volume": 3114.0,
    "sma20": 5880.0,
    "sma50": null,
    "rsi": 48.35,
    "bb_upper": 6268.01,
    "bb_lower": 5491.99,
    "bb_middle": 5880.0,
    "macd": null,
    "macd_signal": null,
    "macd_hist": null
  },
  {
    "date": "2026-05-22",
    "open": 5745.0,
    "high": 5855.0,
    "low": 5745.0,
    "close": 5805.0,
    "volume": 2422.0,
    "sma20": 5881.0,
    "sma50": null,
    "rsi": 51.29,
    "bb_upper": 6268.13,
    "bb_lower": 5493.87,
    "bb_middle": 5881.0,
    "macd": null,
    "macd_signal": null,
    "macd_hist": null
  },
  {
    "date": "2026-05-26",
    "open": 5895.0,
    "high": 6115.0,
    "low": 5895.0,
    "close": 6065.0,
    "volume": 6003.0,
    "sma20": 5889.75,
    "sma50": null,
    "rsi": 57.46,
    "bb_upper": 6285.12,
    "bb_lower": 5494.38,
    "bb_middle": 5889.75,
    "macd": null,
    "macd_signal": null,
    "macd_hist": null
  },
  {
    "date": "2026-05-27",
    "open": 6010.0,
    "high": 6100.0,
    "low": 5930.0,
    "close": 6100.0,
    "volume": 28461.0,
    "sma20": 5889.75,
    "sma50": null,
    "rsi": 58.22,
    "bb_upper": 6285.12,
    "bb_lower": 5494.38,
    "bb_middle": 5889.75,
    "macd": -16.37381921629094,
    "macd_signal": null,
    "macd_hist": null
  },
  {
    "date": "2026-05-28",
    "open": 5985.0,
    "high": 6280.0,
    "low": 5980.0,
    "close": 6270.0,
    "volume": 6059.0,
    "sma20": 5909.75,
    "sma50": null,
    "rsi": 61.82,
    "bb_upper": 6338.18,
    "bb_lower": 5481.32,
    "bb_middle": 5909.75,
    "macd": 16.765435898729265,
    "macd_signal": null,
    "macd_hist": null
  },
  {
    "date": "2026-05-29",
    "open": 6245.0,
    "high": 6280.0,
    "low": 6125.0,
    "close": 6155.0,
    "volume": 8067.0,
    "sma20": 5931.5,
    "sma50": null,
    "rsi": 58.17,
    "bb_upper": 6363.35,
    "bb_lower": 5499.65,
    "bb_middle": 5931.5,
    "macd": 33.3643914914237,
    "macd_signal": null,
    "macd_hist": null
  },
  {
    "date": "2026-06-01",
    "open": 6180.0,
    "high": 6410.0,
    "low": 6120.0,
    "close": 6365.0,
    "volume": 6931.0,
    "sma20": 5953.0,
    "sma50": null,
    "rsi": 62.53,
    "bb_upper": 6424.41,
    "bb_lower": 5481.59,
    "bb_middle": 5953.0,
    "macd": 62.74118699576957,
    "macd_signal": null,
    "macd_hist": null
  },
  {
    "date": "2026-06-02",
    "open": 6385.0,
    "high": 6665.0,
    "low": 6385.0,
    "close": 6630.0,
    "volume": 39986.0,
    "sma20": 5992.0,
    "sma50": null,
    "rsi": 67.17,
    "bb_upper": 6544.89,
    "bb_lower": 5439.11,
    "bb_middle": 5992.0,
    "macd": 106.18179672714177,
    "macd_signal": null,
    "macd_hist": null
  },
  {
    "date": "2026-06-03",
    "open": 6590.0,
    "high": 6600.0,
    "low": 6420.0,
    "close": 6490.0,
    "volume": 6911.0,
    "sma20": 6021.5,
    "sma50": null,
    "rsi": 62.75,
    "bb_upper": 6613.2,
    "bb_lower": 5429.8,
    "bb_middle": 6021.5,
    "macd": 127.83832233745215,
    "macd_signal": null,
    "macd_hist": null
  },
  {
    "date": "2026-06-04",
    "open": 6450.0,
    "high": 6535.0,
    "low": 6385.0,
    "close": 6495.0,
    "volume": 14013.0,
    "sma20": 6039.25,
    "sma50": null,
    "rsi": 62.84,
    "bb_upper": 6664.46,
    "bb_lower": 5414.04,
    "bb_middle": 6039.25,
    "macd": 143.74769912801003,
    "macd_signal": null,
    "macd_hist": null
  },
  {
    "date": "2026-06-05",
    "open": 6495.0,
    "high": 6495.0,
    "low": 5940.0,
    "close": 5940.0,
    "volume": 32821.0,
    "sma20": 6037.25,
    "sma50": null,
    "rsi": 48.26,
    "bb_upper": 6663.46,
    "bb_lower": 5411.04,
    "bb_middle": 6037.25,
    "macd": 110.30065588268553,
    "macd_signal": null,
    "macd_hist": null
  },
  {
    "date": "2026-06-08",
    "open": 6000.0,
    "high": 6085.0,
    "low": 5975.0,
    "close": 6030.0,
    "volume": 8431.0,
    "sma20": 6039.5,
    "sma50": null,
    "rsi": 50.28,
    "bb_upper": 6665.26,
    "bb_lower": 5413.74,
    "bb_middle": 6039.5,
    "macd": 90.0182,
    "macd_signal": 74.9538,
    "macd_hist": 15.0644
  },
  {
    "date": "2026-06-09",
    "open": 6070.0,
    "high": 6070.0,
    "low": 5700.0,
    "close": 5860.0,
    "volume": 4936.0,
    "sma20": 6024.25,
    "sma50": null,
    "rsi": 46.59,
    "bb_upper": 6651.9,
    "bb_lower": 5396.6,
    "bb_middle": 6024.25,
    "macd": 59.5403,
    "macd_signal": 71.8711,
    "macd_hist": -12.3308
  },
  {
    "date": "2026-06-10",
    "open": 5845.0,
    "high": 5890.0,
    "low": 5650.0,
    "close": 5675.0,
    "volume": 7329.0,
    "sma20": 6003.75,
    "sma50": null,
    "rsi": 42.9,
    "bb_upper": 6648.67,
    "bb_lower": 5358.83,
    "bb_middle": 6003.75,
    "macd": 20.2252,
    "macd_signal": 61.5419,
    "macd_hist": -41.3167
  },
  {
    "date": "2026-06-11",
    "open": 5715.0,
    "high": 5885.0,
    "low": 5655.0,
    "close": 5860.0,
    "volume": 2208.0,
    "sma20": 5990.5,
    "sma50": null,
    "rsi": 47.39,
    "bb_upper": 6635.8,
    "bb_lower": 5345.2,
    "bb_middle": 5990.5,
    "macd": 3.9502,
    "macd_signal": 50.0236,
    "macd_hist": -46.0734
  },
  {
    "date": "2026-06-12",
    "open": 6010.0,
    "high": 6075.0,
    "low": 5955.0,
    "close": 6015.0,
    "volume": 3944.0,
    "sma20": 5992.5,
    "sma50": null,
    "rsi": 50.87,
    "bb_upper": 6637.84,
    "bb_lower": 5347.16,
    "bb_middle": 5992.5,
    "macd": 3.5187,
    "macd_signal": 40.7226,
    "macd_hist": -37.2039
  },
  {
    "date": "2026-06-16",
    "open": 6090.0,
    "high": 6090.0,
    "low": 5925.0,
    "close": 5945.0,
    "volume": 4021.0,
    "sma20": 6003.0,
    "sma50": null,
    "rsi": 49.28,
    "bb_upper": 6637.99,
    "bb_lower": 5368.01,
    "bb_middle": 6003.0,
    "macd": -2.4434,
    "macd_signal": 32.0894,
    "macd_hist": -34.5328
  },
  {
    "date": "2026-06-17",
    "open": 5920.0,
    "high": 6120.0,
    "low": 5920.0,
    "close": 5965.0,
    "volume": 3194.0,
    "sma20": 6021.25,
    "sma50": null,
    "rsi": 49.76,
    "bb_upper": 6629.27,
    "bb_lower": 5413.23,
    "bb_middle": 6021.25,
    "macd": -5.4914,
    "macd_signal": 24.5732,
    "macd_hist": -30.0646
  },
  {
    "date": "2026-06-18",
    "open": 6020.0,
    "high": 6020.0,
    "low": 5830.0,
    "close": 5905.0,
    "volume": 1373.0,
    "sma20": 6043.25,
    "sma50": null,
    "rsi": 48.28,
    "bb_upper": 6598.74,
    "bb_lower": 5487.76,
    "bb_middle": 6043.25,
    "macd": -12.6031,
    "macd_signal": 17.138,
    "macd_hist": -29.7411
  },
  {
    "date": "2026-06-19",
    "open": 5665.0,
    "high": 6055.0,
    "low": 5665.0,
    "close": 5900.0,
    "volume": 536.0,
    "sma20": 6058.25,
    "sma50": null,
    "rsi": 48.15,
    "bb_upper": 6580.25,
    "bb_lower": 5536.25,
    "bb_middle": 6058.25,
    "macd": -18.4302,
    "macd_signal": 10.0243,
    "macd_hist": -28.4545
  },
  {
    "date": "2026-06-22",
    "open": 5900.0,
    "high": 5905.0,
    "low": 5800.0,
    "close": 5845.0,
    "volume": 5377.0,
    "sma20": 6065.75,
    "sma50": null,
    "rsi": 46.68,
    "bb_upper": 6570.69,
    "bb_lower": 5560.81,
    "bb_middle": 6065.75,
    "macd": -27.173,
    "macd_signal": 2.5849,
    "macd_hist": -29.7579
  },
  {
    "date": "2026-06-23",
    "open": 5715.0,
    "high": 5805.0,
    "low": 5675.0,
    "close": 5720.0,
    "volume": 5370.0,
    "sma20": 6061.5,
    "sma50": null,
    "rsi": 43.42,
    "bb_upper": 6576.48,
    "bb_lower": 5546.52,
    "bb_middle": 6061.5,
    "macd": -43.6847,
    "macd_signal": -6.669,
    "macd_hist": -37.0157
  },
  {
    "date": "2026-06-24",
    "open": 5660.0,
    "high": 5660.0,
    "low": 5480.0,
    "close": 5515.0,
    "volume": 11972.0,
    "sma20": 6034.0,
    "sma50": null,
    "rsi": 38.66,
    "bb_upper": 6601.37,
    "bb_lower": 5466.63,
    "bb_middle": 6034.0,
    "macd": -72.4766,
    "macd_signal": -19.8306,
    "macd_hist": -52.646
  },
  {
    "date": "2026-06-25",
    "open": 5535.0,
    "high": 5665.0,
    "low": 5520.0,
    "close": 5605.0,
    "volume": 6373.0,
    "sma20": 6009.25,
    "sma50": null,
    "rsi": 41.68,
    "bb_upper": 6605.4,
    "bb_lower": 5413.1,
    "bb_middle": 6009.25,
    "macd": -87.0289,
    "macd_signal": -33.2702,
    "macd_hist": -53.7587
  },
  {
    "date": "2026-06-26",
    "open": 5600.0,
    "high": 5670.0,
    "low": 5495.0,
    "close": 5520.0,
    "volume": 2692.0,
    "sma20": 5971.75,
    "sma50": null,
    "rsi": 39.69,
    "bb_upper": 6591.46,
    "bb_lower": 5352.04,
    "bb_middle": 5971.75,
    "macd": -104.2192,
    "macd_signal": -47.46,
    "macd_hist": -56.7592
  },
  {
    "date": "2026-06-29",
    "open": 5565.0,
    "high": 5565.0,
    "low": 5435.0,
    "close": 5535.0,
    "volume": 7097.0,
    "sma20": 5940.75,
    "sma50": null,
    "rsi": 40.24,
    "bb_upper": 6582.34,
    "bb_lower": 5299.16,
    "bb_middle": 5940.75,
    "macd": -115.303,
    "macd_signal": -61.0286,
    "macd_hist": -54.2744
  },
  {
    "date": "2026-06-30",
    "open": 5525.0,
    "high": 5600.0,
    "low": 5470.0,
    "close": 5545.0,
    "volume": 2691.0,
    "sma20": 5899.75,
    "sma50": null,
    "rsi": 40.62,
    "bb_upper": 6532.39,
    "bb_lower": 5267.11,
    "bb_middle": 5899.75,
    "macd": -121.8753,
    "macd_signal": -73.198,
    "macd_hist": -48.6773
  },
  {
    "date": "2026-07-01",
    "open": 5525.0,
    "high": 5655.0,
    "low": 5465.0,
    "close": 5490.0,
    "volume": 1584.0,
    "sma20": 5842.75,
    "sma50": 5906.3,
    "rsi": 39.13,
    "bb_upper": 6403.25,
    "bb_lower": 5282.25,
    "bb_middle": 5842.75,
    "macd": -130.023,
    "macd_signal": -84.563,
    "macd_hist": -45.46
  },
  {
    "date": "2026-07-02",
    "open": 5675.0,
    "high": 5745.0,
    "low": 5410.0,
    "close": 5485.0,
    "volume": 3281.0,
    "sma20": 5792.5,
    "sma50": 5901.5,
    "rsi": 38.99,
    "bb_upper": 6288.36,
    "bb_lower": 5296.64,
    "bb_middle": 5792.5,
    "macd": -135.3237,
    "macd_signal": -94.7151,
    "macd_hist": -40.6086
  },
  {
    "date": "2026-07-03",
    "open": 5650.0,
    "high": 5680.0,
    "low": 5385.0,
    "close": 5665.0,
    "volume": 219.0,
    "sma20": 5751.0,
    "sma50": 5899.7,
    "rsi": 46.41,
    "bb_upper": 6129.86,
    "bb_lower": 5372.14,
    "bb_middle": 5751.0,
    "macd": -123.5756,
    "macd_signal": -100.4872,
    "macd_hist": -23.0884
  },
  {
    "date": "2026-07-06",
    "open": 5615.0,
    "high": 5615.0,
    "low": 5505.0,
    "close": 5580.0,
    "volume": 4912.0,
    "sma20": 5733.0,
    "sma50": 5891.5,
    "rsi": 43.71,
    "bb_upper": 6108.43,
    "bb_lower": 5357.57,
    "bb_middle": 5733.0,
    "macd": -119.7435,
    "macd_signal": -104.3385,
    "macd_hist": -15.405
  },
  {
    "date": "2026-07-07",
    "open": 5495.0,
    "high": 5495.0,
    "low": 5300.0,
    "close": 5380.0,
    "volume": 10058.0,
    "sma20": 5700.5,
    "sma50": 5883.4,
    "rsi": 38.09,
    "bb_upper": 6079.97,
    "bb_lower": 5321.03,
    "bb_middle": 5700.5,
    "macd": -131.331,
    "macd_signal": -109.737,
    "macd_hist": -21.594
  },
  {
    "date": "2026-07-08",
    "open": 5350.0,
    "high": 5395.0,
    "low": 5220.0,
    "close": 5370.0,
    "volume": 7952.0,
    "sma20": 5676.0,
    "sma50": 5873.0,
    "rsi": 37.83,
    "bb_upper": 6073.94,
    "bb_lower": 5278.06,
    "bb_middle": 5676.0,
    "macd": -139.7106,
    "macd_signal": -115.7317,
    "macd_hist": -23.9789
  },
  {
    "date": "2026-07-10",
    "open": 5415.0,
    "high": 5455.0,
    "low": 5370.0,
    "close": 5430.0,
    "volume": 249.0,
    "sma20": 5663.75,
    "sma50": 5859.6,
    "rsi": 40.47,
    "bb_upper": 6075.89,
    "bb_lower": 5251.61,
    "bb_middle": 5663.75,
    "macd": -139.8974,
    "macd_signal": -120.5648,
    "macd_hist": -19.3326
  },
  {
    "date": "2026-07-13",
    "open": 5415.0,
    "high": 5420.0,
    "low": 5305.0,
    "close": 5315.0,
    "volume": 2097.0,
    "sma20": 5636.5,
    "sma50": 5848.5,
    "rsi": 37.2,
    "bb_upper": 6064.88,
    "bb_lower": 5208.12,
    "bb_middle": 5636.5,
    "macd": -147.6232,
    "macd_signal": -125.9765,
    "macd_hist": -21.6467
  },
  {
    "date": "2026-07-14",
    "open": 5500.0,
    "high": 5505.0,
    "low": 5380.0,
    "close": 5420.0,
    "volume": 1982.0,
    "sma20": 5606.75,
    "sma50": 5842.5,
    "rsi": 41.82,
    "bb_upper": 6007.62,
    "bb_lower": 5205.88,
    "bb_middle": 5606.75,
    "macd": -143.6178,
    "macd_signal": -129.5048,
    "macd_hist": -14.113
  },
  {
    "date": "2026-07-15",
    "open": 5475.0,
    "high": 5475.0,
    "low": 5280.0,
    "close": 5380.0,
    "volume": 1467.0,
    "sma20": 5578.5,
    "sma50": 5831.4,
    "rsi": 40.6,
    "bb_upper": 5959.16,
    "bb_lower": 5197.84,
    "bb_middle": 5578.5,
    "macd": -142.0339,
    "macd_signal": -132.0106,
    "macd_hist": -10.0233
  },
  {
    "date": "2026-07-16",
    "open": 5305.0,
    "high": 5305.0,
    "low": 5130.0,
    "close": 5150.0,
    "volume": 827.0,
    "sma20": 5537.75,
    "sma50": 5817.4,
    "rsi": 34.37,
    "bb_upper": 5918.68,
    "bb_lower": 5156.82,
    "bb_middle": 5537.75,
    "macd": -157.5219,
    "macd_signal": -137.1129,
    "macd_hist": -20.409
  },
  {
    "date": "2026-07-17",
    "open": 5135.0,
    "high": 5175.0,
    "low": 5040.0,
    "close": 5140.0,
    "volume": 1192.0,
    "sma20": 5499.5,
    "sma50": 5802.2,
    "rsi": 34.12,
    "bb_upper": 5878.87,
    "bb_lower": 5120.13,
    "bb_middle": 5499.5,
    "macd": -168.659,
    "macd_signal": -143.4221,
    "macd_hist": -25.2369
  }
]